README.rst
flask_failsafe.py
setup.py
Flask_Failsafe.egg-info/PKG-INFO
Flask_Failsafe.egg-info/SOURCES.txt
Flask_Failsafe.egg-info/dependency_links.txt
Flask_Failsafe.egg-info/requires.txt
Flask_Failsafe.egg-info/top_level.txt
Flask_Failsafe.egg-info/zip-safe
test/test_app.py