Metadata-Version: 1.0
Name: Flask-Failsafe
Version: 0.2
Summary: A failsafe for the Flask reloader
Home-page: http://github.com/mgood/flask-failsafe
Author: Matt Good
Author-email: matt@matt-good.net
License: BSD
Platform: any
